daag/__init__.py
daag/core.py
daag/visualization.py
tests/__init__.py
tests/example.py
tests/test_daag.py
daag-0.1.2.dist-info/LICENSE
daag-0.1.2.dist-info/METADATA
daag-0.1.2.dist-info/WHEEL
daag-0.1.2.dist-info/top_level.txt
daag-0.1.2.dist-info/RECORD
