Metadata-Version: 2.2
Name: daag
Version: 0.1.2
Summary: A Python library for creating, visualizing, and manipulating Directed Acyclic Adjacency Graphs - specialized graphs where edges are directed, no cycles are allowed, and edges only connect vertices in adjacent layers.
Author-email: santiagosayshey <schau22@example.com>
License: MIT
Project-URL: Homepage, https://github.com/Dictionarry-Hub/daag
Project-URL: Bug Tracker, https://github.com/Dictionarry-Hub/daag/issues
Classifier: Programming Language :: Python :: 3
Classifier: License :: OSI Approved :: MIT License
Classifier: Operating System :: OS Independent
Requires-Python: >=3.7
License-File: LICENSE
Requires-Dist: networkx
Requires-Dist: matplotlib
